{
  "project_info": {
    "project_number": "717685951388",
    "project_id": "pickleball-c5325",
    "storage_bucket": "pickleball-c5325.firebasestorage.app"
  },
  "client": [
    {
      "client_info": {
        "mobilesdk_app_id": "1:717685951388:android:b1cfae4857b8221402d659",
        "android_client_info": {
          "package_name": "com.example.pickleball"
        }
      },
      "oauth_client": [
        {
          "client_id": "717685951388-7vkmpp4j0fjo0k2bfn9rs7a0kgs5klev.apps.googleusercontent.com",
          "client_type": 1,
          "android_info": {
            "package_name": "com.example.pickleball",
            "certificate_hash": "4ddc3f49cca27b6963c2a29ce6871e53e4c0b17b"
          }
        },
        {
          "client_id": "717685951388-fj4qvq1iisal0rj0epmqkubpu23umtm0.apps.googleusercontent.com",
          "client_type": 3
        }
      ],
      "api_key": [
        {
          "current_key": "AIzaSyCQDxf0WZP0powHTv2VnHNICmeFOJ8NFqs"
        }
      ],
      "services": {
        "appinvite_service": {
          "other_platform_oauth_client": [
            {
              "client_id": "717685951388-fj4qvq1iisal0rj0epmqkubpu23umtm0.apps.googleusercontent.com",
              "client_type": 3
            }
          ]
        }
      }
    }
  ],
  "configuration_version": "1"
}